.readthedocs.yml
CHANGELOG.txt
LICENSE
MANIFEST.in
README.md
pyproject.toml
requirements.txt
setup.py
docs/Makefile
docs/WASP18b_eclipse.rst
docs/conf.py
docs/contributing.rst
docs/index.rst
docs/install.rst
docs/license.rst
docs/make.bat
docs/pup_marker.rst
docs/figures/.DS_Store
docs/figures/logo_puppies_texted.png
docs/figures/logo_puppies_untexted.png
docs/figures/pup_markers.png
docs/figures/puppies_favicon.ico
docs/figures/wasp18b_best_light_curve.png
docs/figures/wasp18b_centering.png
docs/figures/wasp18b_init.png
docs/figures/wasp18b_photometry.png
docs/figures/wasp18b_posterior_light_curve.png
exo_puppies.egg-info/PKG-INFO
exo_puppies.egg-info/SOURCES.txt
exo_puppies.egg-info/dependency_links.txt
exo_puppies.egg-info/entry_points.txt
exo_puppies.egg-info/requires.txt
exo_puppies.egg-info/top_level.txt
puppies/__init__.py
puppies/__main__.py
puppies/laika.py
puppies/version.py
puppies/center/__init__.py
puppies/center/center_of_light.py
puppies/center/driver.py
puppies/center/least_asym.py
puppies/center/psf_gauss.py
puppies/center/gaussian/__init__.py
puppies/center/gaussian/gaussian.py
puppies/core/__init__.py
puppies/core/pup_badpix.py
puppies/core/pup_center.py
puppies/core/pup_model.py
puppies/core/pup_photom.py
puppies/data/dogs_of_the_day.txt
puppies/data/spitzer_filters/irac1_filter.dat
puppies/data/spitzer_filters/irac2_filter.dat
puppies/data/spitzer_filters/irac3_filter.dat
puppies/data/spitzer_filters/irac4_filter.dat
puppies/data/spitzer_filters/irs-blue_filter.dat
puppies/data/spitzer_filters/mips-24um_filter.dat
puppies/data/spitzer_psf/IRAC.1.PRF.5X.070312.fits
puppies/data/spitzer_psf/IRAC.2.PRF.5X.070312.fits
puppies/data/spitzer_psf/IRAC.3.PRF.5X.070312.fits
puppies/data/spitzer_psf/IRAC.4.PRF.5X.070312.fits
puppies/data/spitzer_psf/IRS_BPUI_PSF.fits
puppies/image/__init__.py
puppies/image/disk.py
puppies/image/imedit.py
puppies/instruments/__init__.py
puppies/instruments/pup_spitzer.py
puppies/io/__init__.py
puppies/io/io.py
puppies/models/__init__.py
puppies/models/aor.py
puppies/models/ballardip.py
puppies/models/bliss.py
puppies/models/eclipse.py
puppies/models/ipspline.py
puppies/models/mandeltr.py
puppies/models/ophase.py
