Metadata-Version: 2.1
Name: exo_puppies
Version: 0.5.0
Summary: The Public Photometry Pipeline for Exoplanets
Author-email: Patricio Cubillos <pcubillos@fulbrightmail.org>
License:                     GNU GENERAL PUBLIC LICENSE
Project-URL: Homepage, https://github.com/pcubillos/puppies
Requires-Python: >=3.7
License-File: LICENSE
Requires-Dist: numpy>=1.13.3
Requires-Dist: scipy>=1.4.1
Requires-Dist: matplotlib>=1.3.1
Requires-Dist: astropy>=3.1
Requires-Dist: mc3>=3.0.12
Provides-Extra: test
Requires-Dist: pytest>=3.9; extra == "test"
